hermessmiles/__init__.py
hermessmiles/athena_smiles_standardisation.py
hermessmiles/cli.py
hermessmiles/processor.py
hermessmiles/visualizer.py
tests/__init__.py
tests/test_processor.py
tests/test_visualizer.py
hermessmiles-0.1.4.dist-info/METADATA
hermessmiles-0.1.4.dist-info/WHEEL
hermessmiles-0.1.4.dist-info/entry_points.txt
hermessmiles-0.1.4.dist-info/top_level.txt
hermessmiles-0.1.4.dist-info/RECORD
